osdr.py
ftd600/__init__.py
ftd600/_ftd3xx_linux.py
ftd600/_ftd3xx_win32.py
ftd600/defines.py
ftd600/ftd3xx.py
osdr-1.0.2.dist-info/LICENSE
osdr-1.0.2.dist-info/METADATA
osdr-1.0.2.dist-info/WHEEL
osdr-1.0.2.dist-info/top_level.txt
osdr-1.0.2.dist-info/RECORD
