Metadata-Version: 2.1
Name: osdr
Version: 1.0.2
Summary: osdr package
Home-page: https://github.com/pypa/sampleproject
Author: orion
Author-email: osdr@orion.com
License: UNKNOWN
Platform: UNKNOWN
Classifier: Programming Language :: Python :: 3
Classifier: License :: OSI Approved :: MIT License
Classifier: Operating System :: OS Independent
